{
  "name": "Principled (Striker)",
  "type": "talent",
  "img": "icons/svg/item-bag.svg",
  "system": {
    "description": "When you act driven by your motive, you can add 1d6 to your dice pool.",
    "archetype": "striker",
    "talentLevel": 1,
    "prerequisite": "",
    "diceBonus": {
      "amount": 1,
      "rollType": "any",
      "condition": "When acting driven by your motive"
    },
    "willBonus": 0,
    "uses": {
      "per": "unlimited",
      "max": 0,
      "current": 0
    },
    "isCrossTraining": false,
    "sourceArchetype": ""
  },
  "effects": [],
  "folder": "sQPmIvXiamDz8gSw",
  "flags": {},
  "_stats": {
    "compendiumSource": "Compendium.paragons.talents.Item.j7Y4oLkHYBPFKOOr",
    "duplicateSource": null,
    "exportSource": {
      "worldId": "paragons-provisional",
      "uuid": "Item.Lqk9mYz7y30op8dw",
      "coreVersion": "13.351",
      "systemId": "paragons",
      "systemVersion": "0.2.0"
    },
    "coreVersion": "13.351",
    "systemId": "paragons",
    "systemVersion": "0.2.0",
    "createdTime": 1778814114461,
    "modifiedTime": 1778814114461,
    "lastModifiedBy": "MuIQ6Rg5mgZrRQWa"
  },
  "ownership": {
    "default": 0
  }
}